mql/__init__.py
mql/base.py
mql/operators/base.py
mql/operators/query/__init__.py
mql/operators/query/array/__init__.py
mql/operators/query/array/all.py
mql/operators/query/array/elem_match.py
mql/operators/query/array/size.py
mql/operators/query/bitwise/__init__.py
mql/operators/query/comparison/__init__.py
mql/operators/query/comparison/eq.py
mql/operators/query/comparison/gt.py
mql/operators/query/comparison/gte.py
mql/operators/query/comparison/in_.py
mql/operators/query/comparison/lt.py
mql/operators/query/comparison/lte.py
mql/operators/query/comparison/ne.py
mql/operators/query/comparison/nin.py
mql/operators/query/element/__init__.py
mql/operators/query/element/exists.py
mql/operators/query/element/type.py
mql/operators/query/evaluation/__init__.py
mql/operators/query/evaluation/expr.py
mql/operators/query/evaluation/json_schema.py
mql/operators/query/evaluation/mod.py
mql/operators/query/evaluation/regex.py
mql/operators/query/evaluation/where.py
mql/operators/query/geospatial/__init__.py
mql/operators/query/logical/__init__.py
mql/operators/query/logical/and_.py
mql/operators/query/logical/nor.py
mql/operators/query/logical/not_.py
mql/operators/query/logical/or_.py
mql/operators/query/miscellaneous/__init__.py
mql/operators/query/projection/__init__.py
mql/operators/query/projection/elem_match.py
mql/operators/query/projection/positional.py
mql/operators/query/projection/slice.py
mql/operators/update/array/all_positional.py
mql/operators/update/array/filtered_positional.py
mql/operators/update/array/positional.py
mql/operators/update/array/modifiers/each.py
mql/operators/update/array/modifiers/position.py
mql/operators/update/array/modifiers/slice.py
mql/operators/update/array/modifiers/sort.py
mql/operators/update/arrays/__init__.py
mql/operators/update/arrays/add_to_set.py
mql/operators/update/arrays/pop.py
mql/operators/update/arrays/pull.py
mql/operators/update/arrays/pull_all.py
mql/operators/update/arrays/push.py
mongoql-0.0.1.dist-info/LICENSE
mongoql-0.0.1.dist-info/METADATA
mongoql-0.0.1.dist-info/WHEEL
mongoql-0.0.1.dist-info/top_level.txt
mongoql-0.0.1.dist-info/RECORD
