Metadata-Version: 2.2
Name: mongoql
Version: 0.0.1
Summary: MongoDB Query Language Builder
Author-email: Vianney Mixtur <vianney.mixtur@outlook.fr>
License: MIT
Project-URL: Homepage, https://github.com/VianneyMI/mql
Project-URL: Repository, https://github.com/VianneyMI/mql
Classifier: Development Status :: 3 - Alpha
Classifier: Intended Audience :: Developers
Classifier: License :: OSI Approved :: MIT License
Classifier: Operating System :: OS Independent
Classifier: Programming Language :: Python
Classifier: Programming Language :: Python :: 3
Classifier: Programming Language :: Python :: 3.8
Classifier: Programming Language :: Python :: 3.9
Classifier: Programming Language :: Python :: 3.10
Classifier: Programming Language :: Python :: 3.11
Classifier: Topic :: Database
Classifier: Topic :: Software Development :: Libraries :: Python Modules
Requires-Python: >=3.8
License-File: LICENSE
Requires-Dist: pydantic>=2.0.0
